setup.py
desk_probability/Binomialdistribution.py
desk_probability/Gaussiandistribution.py
desk_probability/Generaldistribution.py
desk_probability/__init__.py
desk_probability.egg-info/PKG-INFO
desk_probability.egg-info/SOURCES.txt
desk_probability.egg-info/dependency_links.txt
desk_probability.egg-info/not-zip-safe
desk_probability.egg-info/top_level.txt