Metadata-Version: 1.0
Name: desk-probability
Version: 0.1
Summary: Gaussian (a.k.a., Normal) and Binomial probability distributions
Home-page: UNKNOWN
Author: Sankar Ray
Author-email: UNKNOWN
License: UNKNOWN
Platform: UNKNOWN
